langgraph/checkpoint/oceanbase/__init__.py
langgraph/checkpoint/oceanbase/_ainternal.py
langgraph/checkpoint/oceanbase/_internal.py
langgraph/checkpoint/oceanbase/aio.py
langgraph/checkpoint/oceanbase/aio_base.py
langgraph/checkpoint/oceanbase/asyncmy.py
langgraph/checkpoint/oceanbase/base.py
langgraph/checkpoint/oceanbase/py.typed
langgraph/checkpoint/oceanbase/pyoceanbase.py
langgraph/checkpoint/oceanbase/shallow.py
langgraph/checkpoint/oceanbase/utils.py
langgraph/store/oceanbase/__init__.py
langgraph/store/oceanbase/aio.py
langgraph/store/oceanbase/aio_base.py
langgraph/store/oceanbase/asyncmy.py
langgraph/store/oceanbase/base.py
langgraph/store/oceanbase/py.typed
langgraph/store/oceanbase/pyoceanbase.py
langgraph_checkpoint_oceanbase-2.0.18.dist-info/METADATA
langgraph_checkpoint_oceanbase-2.0.18.dist-info/WHEEL
langgraph_checkpoint_oceanbase-2.0.18.dist-info/licenses/LICENSE
langgraph_checkpoint_oceanbase-2.0.18.dist-info/RECORD
