Metadata-Version: 2.4
Name: langgraph-checkpoint-oceanbase
Version: 2.0.18
Summary: Library with a OceanBase MySQL Mode implementation of LangGraph checkpoint saver.
Project-URL: Repository, https://www.github.com/davidzhangbj/langgraph-checkpoint-mysql
Author: David Zhang
License-Expression: MIT
License-File: LICENSE
Requires-Python: >=3.9
Requires-Dist: langgraph-checkpoint>=2.0.21
Requires-Dist: orjson>=3.10.1
Requires-Dist: typing-extensions>=4.12.2
Provides-Extra: aiomysql
Requires-Dist: aiomysql>=0.2.0; extra == 'aiomysql'
Provides-Extra: asyncmy
Requires-Dist: asyncmy>=0.2.10; extra == 'asyncmy'
Provides-Extra: pymysql
Requires-Dist: pymysql>=1.1.1; extra == 'pymysql'
